MANIFEST.in
README.rst
requirements.txt
setup.py
downloader_cluster/__init__.py
downloader_cluster/downloader.py
downloader_cluster/multi_download_process.py
downloader_cluster/settings.py
downloader_cluster.egg-info/PKG-INFO
downloader_cluster.egg-info/SOURCES.txt
downloader_cluster.egg-info/dependency_links.txt
downloader_cluster.egg-info/entry_points.txt
downloader_cluster.egg-info/requires.txt
downloader_cluster.egg-info/top_level.txt
downloader_cluster.egg-info/zip-safe
test/test.py