Metadata-Version: 1.1
Name: downloader-cluster
Version: 1.0.6
Summary: 一个简单的支持多线程，断点续传及分布式的下载器。 
Home-page: https://www.github.com/ShichaoMa/downloader_cluster
Author: cn
Author-email: 308299269@qq.com
License: MIT
Keywords: downloader cluster download
Platform: UNKNOWN
Classifier: License :: OSI Approved :: MIT License
Classifier: Programming Language :: Python
Classifier: Intended Audience :: Developers
Classifier: Operating System :: OS Independent
